lsp_search/__init__.py
lsp_search-0.0.2.dist-info/METADATA
lsp_search-0.0.2.dist-info/WHEEL
lsp_search-0.0.2.dist-info/entry_points.txt
lsp_search-0.0.2.dist-info/top_level.txt
lsp_search-0.0.2.dist-info/RECORD
