Metadata-Version: 2.1
Name: lsp-search
Version: 0.0.2
Summary: Open your lsp soul.
Home-page: https://github.com/Jormungendr/lsp_search
Author: fenrisu1fr
Author-email: simth.rock@8iy3.onmicrosoft.com
License: UNKNOWN
Platform: UNKNOWN
Requires-Dist: bs4
